cyrecon/__init__.py
cyrecon/ai_classifier.py
cyrecon/dirscanner.py
cyrecon/main.py
cyrecon/portscanner.py
cyrecon/reportgen.py
cyrecon/screenshooter.py
cyrecon/subdomains.py
cyrecon/vulnmatcher.py
cyrecon/models/model.onnx
cyrecon-1.0.8.dist-info/METADATA
cyrecon-1.0.8.dist-info/WHEEL
cyrecon-1.0.8.dist-info/entry_points.txt
cyrecon-1.0.8.dist-info/top_level.txt
cyrecon-1.0.8.dist-info/RECORD
