Metadata-Version: 2.1
Name: cyrecon
Version: 1.0.8
Requires-Dist: requests
Requires-Dist: tqdm
Requires-Dist: selenium
Requires-Dist: fpdf
Requires-Dist: colorama
Requires-Dist: onnxruntime
Requires-Dist: tldextract
Requires-Dist: numpy
